Qtalk/__init__.py
Qtalk/alert_manager.py
Qtalk/integration.py
Qtalk-2.0.dist-info/METADATA
Qtalk-2.0.dist-info/WHEEL
Qtalk-2.0.dist-info/top_level.txt
Qtalk-2.0.dist-info/RECORD
