Metadata-Version: 2.1
Name: Qtalk
Version: 2.0
Summary: Mattermost integration package
Home-page: UNKNOWN
Author: Lucia Kina
Author-email: <lkina@quanticotrends.com>
License: UNKNOWN
Keywords: python,mattermost,alerts,qtalk
Platform: UNKNOWN
Classifier: Development Status :: 4 - Beta
Classifier: Intended Audience :: Developers
Classifier: Programming Language :: Python :: 3
Classifier: Operating System :: MacOS :: MacOS X
Classifier: Operating System :: Microsoft :: Windows
